quo/__init__.py
quo/__main__.py
quo/__spinners.py
quo/_spinners.py
quo/accordance.py
quo/argparse.py
quo/bar.py
quo/box.py
quo/buffer.py
quo/button.py
quo/consoleapp.py
quo/dialog.py
quo/document.py
quo/enums.py
quo/errors.py
quo/event.py
quo/frame.py
quo/history.py
quo/implementation.py
quo/label.py
quo/log.py
quo/main.py
quo/mouse_events.py
quo/parse.py
quo/parser.py
quo/patch_stdout.py
quo/pause.py
quo/prompt.py
quo/renderer.py
quo/rmreplica.py
quo/rule.py
quo/rules.py
quo/search.py
quo/selection.py
quo/setout.py
quo/shelldone.py
quo/something.py
quo/spin.py
quo/syntax.py
quo/table.py
quo/template.py
quo/textfield.py
quo/toolbar.py
quo/types.py
quo/universal.py
quo/win32_types.py
quo/window.py
quo/cache/__init__.py
quo/cache/_lru_cache.py
quo/cache/core.py
quo/clipboard/__init__.py
quo/clipboard/core.py
quo/clipboard/momento.py
quo/clipboard/pyperclip.py
quo/color/__init__.py
quo/color/ansi.py
quo/color/rgb.py
quo/completion/__init__.py
quo/completion/auto_suggest.py
quo/completion/core.py
quo/completion/deduplicate.py
quo/completion/filesystem.py
quo/completion/fuzzy_completer.py
quo/completion/nested.py
quo/completion/word_completer.py
quo/console/__init__.py
quo/console/console.py
quo/console/current.py
quo/console/dummy.py
quo/console/run_in_terminal.py
quo/context/__init__.py
quo/context/current.py
quo/contrib/__init__.py
quo/contrib/completers/__init__.py
quo/contrib/completers/system.py
quo/contrib/regular_languages/__init__.py
quo/contrib/regular_languages/compiler.py
quo/contrib/regular_languages/completion.py
quo/contrib/regular_languages/lexer.py
quo/contrib/regular_languages/regex_parser.py
quo/contrib/regular_languages/validation.py
quo/contrib/ssh/__init__.py
quo/contrib/ssh/server.py
quo/contrib/telnet/__init__.py
quo/contrib/telnet/log.py
quo/contrib/telnet/protocol.py
quo/contrib/telnet/server.py
quo/decorators/__init__.py
quo/decorators/autoconfirm.py
quo/decorators/autohelp.py
quo/decorators/autopasswd.py
quo/decorators/autoversion.py
quo-2023.5.1.dist-info/LICENSE
quo-2023.5.1.dist-info/METADATA
quo-2023.5.1.dist-info/WHEEL
quo-2023.5.1.dist-info/top_level.txt
quo-2023.5.1.dist-info/RECORD
