Metadata-Version: 2.1
Name: quo
Version: 2023.5.1
Summary: Toolkit for writing Command-Line Interface applications and a Text User Interface framework for Python.
Home-page: https://quo.rtfd.io
Author: Gerrishon Sirere
Author-email: scalabli@proton.me
Maintainer: Scalabli.
Maintainer-email: scalabli@proton.me
License: MIT
Project-URL: Donate, https://ko-fi.com/scalabli
Project-URL: Documentation, https://quo.rtfd.io
Project-URL: Changes, https://quo.readthedocs.io/en/latest/changes.html
Project-URL: Source Code, https://github.com/scalabli/quo
Project-URL: Issue Tracker, https://github.com/scalabli/quo/issues/
Project-URL: Twitter, https://twitter.com/scalabli
Project-URL: Chat, https://gitter.im/scalabli
Platform: UNKNOWN
Classifier: Development Status :: 5 - Production/Stable
Classifier: Intended Audience :: Developers
Classifier: Environment :: Console
Classifier: License :: OSI Approved :: MIT License
Classifier: Operating System :: OS Independent
Classifier: Programming Language :: Python :: 3.8
Classifier: Programming Language :: Python :: 3.9
Classifier: Programming Language :: Python :: 3.10
Classifier: Programming Language :: Python :: 3.11
Requires-Python: >=3.8
License-File: LICENSE
Requires-Dist: pygments
Requires-Dist: termcolor
Requires-Dist: colorama ; platform_system == "Windows"
